<?xml version="1.0" encoding="UTF-8"?>
<issues format="6" by="lint 8.4.1" type="baseline" client="gradle" dependencies="false" name="AGP (8.4.1)" variant="all" version="8.4.1">

    <issue
        id="NewApi"
        message="Call requires API level 33 (current min is 24): `android.os.Bundle#getParcelable`"
        errorLine1="        arguments?.getParcelable(&quot;task&quot;, Task::class.java)?.let {"
        errorLine2="                   ~~~~~~~~~~~~~">
        <location
            file="src/main/java/io/junrdev/github/taskee/screens/EditTask.kt"
            line="68"
            column="20"/>
    </issue>

    <issue
        id="OldTargetApi"
        message="Not targeting the latest versions of Android; compatibility modes apply. Consider testing and updating this version. Consult the `android.os.Build.VERSION_CODES` javadoc for details."
        errorLine1="        targetSdk = 34"
        errorLine2="        ~~~~~~~~~~~~~~">
        <location
            file="build.gradle.kts"
            line="17"
            column="9"/>
    </issue>

    <issue
        id="AndroidGradlePluginVersion"
        message="A newer version of com.android.application than 8.4.1 is available: 8.5.1. (There is also a newer version of 8.4.ð‘¥ available, if upgrading to 8.5.1 is difficult: 8.4.2)"
        errorLine1="agp = &quot;8.4.1&quot;"
        errorLine2="      ~~~~~~~">
        <location
            file="../gradle/libs.versions.toml"
            line="2"
            column="7"/>
    </issue>

    <issue
        id="AndroidGradlePluginVersion"
        message="A newer version of com.android.application than 8.4.1 is available: 8.5.1. (There is also a newer version of 8.4.ð‘¥ available, if upgrading to 8.5.1 is difficult: 8.4.2)"
        errorLine1="agp = &quot;8.4.1&quot;"
        errorLine2="      ~~~~~~~">
        <location
            file="../gradle/libs.versions.toml"
            line="2"
            column="7"/>
    </issue>

    <issue
        id="AndroidGradlePluginVersion"
        message="A newer version of com.android.application than 8.4.1 is available: 8.5.1. (There is also a newer version of 8.4.ð‘¥ available, if upgrading to 8.5.1 is difficult: 8.4.2)"
        errorLine1="agp = &quot;8.4.1&quot;"
        errorLine2="      ~~~~~~~">
        <location
            file="../gradle/libs.versions.toml"
            line="2"
            column="7"/>
    </issue>

    <issue
        id="GradleDependency"
        message="A newer version of androidx.test.ext:junit than 1.1.5 is available: 1.2.1"
        errorLine1="junitVersion = &quot;1.1.5&quot;"
        errorLine2="               ~~~~~~~">
        <location
            file="../gradle/libs.versions.toml"
            line="7"
            column="16"/>
    </issue>

    <issue
        id="GradleDependency"
        message="A newer version of androidx.test.ext:junit than 1.1.5 is available: 1.2.1"
        errorLine1="junitVersion = &quot;1.1.5&quot;"
        errorLine2="               ~~~~~~~">
        <location
            file="../gradle/libs.versions.toml"
            line="7"
            column="16"/>
    </issue>

    <issue
        id="GradleDependency"
        message="A newer version of androidx.test.ext:junit than 1.1.5 is available: 1.2.1"
        errorLine1="junitVersion = &quot;1.1.5&quot;"
        errorLine2="               ~~~~~~~">
        <location
            file="../gradle/libs.versions.toml"
            line="7"
            column="16"/>
    </issue>

    <issue
        id="GradleDependency"
        message="A newer version of androidx.test.espresso:espresso-core than 3.5.1 is available: 3.6.1"
        errorLine1="espressoCore = &quot;3.5.1&quot;"
        errorLine2="               ~~~~~~~">
        <location
            file="../gradle/libs.versions.toml"
            line="8"
            column="16"/>
    </issue>

    <issue
        id="GradleDependency"
        message="A newer version of androidx.test.espresso:espresso-core than 3.5.1 is available: 3.6.1"
        errorLine1="espressoCore = &quot;3.5.1&quot;"
        errorLine2="               ~~~~~~~">
        <location
            file="../gradle/libs.versions.toml"
            line="8"
            column="16"/>
    </issue>

    <issue
        id="GradleDependency"
        message="A newer version of androidx.test.espresso:espresso-core than 3.5.1 is available: 3.6.1"
        errorLine1="espressoCore = &quot;3.5.1&quot;"
        errorLine2="               ~~~~~~~">
        <location
            file="../gradle/libs.versions.toml"
            line="8"
            column="16"/>
    </issue>

    <issue
        id="GradleDependency"
        message="A newer version of androidx.appcompat:appcompat than 1.6.1 is available: 1.7.0"
        errorLine1="appcompat = &quot;1.6.1&quot;"
        errorLine2="            ~~~~~~~">
        <location
            file="../gradle/libs.versions.toml"
            line="9"
            column="13"/>
    </issue>

    <issue
        id="GradleDependency"
        message="A newer version of androidx.appcompat:appcompat than 1.6.1 is available: 1.7.0"
        errorLine1="appcompat = &quot;1.6.1&quot;"
        errorLine2="            ~~~~~~~">
        <location
            file="../gradle/libs.versions.toml"
            line="9"
            column="13"/>
    </issue>

    <issue
        id="GradleDependency"
        message="A newer version of androidx.appcompat:appcompat than 1.6.1 is available: 1.7.0"
        errorLine1="appcompat = &quot;1.6.1&quot;"
        errorLine2="            ~~~~~~~">
        <location
            file="../gradle/libs.versions.toml"
            line="9"
            column="13"/>
    </issue>

    <issue
        id="GradleDependency"
        message="A newer version of com.google.android.material:material than 1.10.0 is available: 1.12.0"
        errorLine1="material = &quot;1.10.0&quot;"
        errorLine2="           ~~~~~~~~">
        <location
            file="../gradle/libs.versions.toml"
            line="10"
            column="12"/>
    </issue>

    <issue
        id="GradleDependency"
        message="A newer version of com.google.android.material:material than 1.10.0 is available: 1.12.0"
        errorLine1="material = &quot;1.10.0&quot;"
        errorLine2="           ~~~~~~~~">
        <location
            file="../gradle/libs.versions.toml"
            line="10"
            column="12"/>
    </issue>

    <issue
        id="GradleDependency"
        message="A newer version of com.google.android.material:material than 1.10.0 is available: 1.12.0"
        errorLine1="material = &quot;1.10.0&quot;"
        errorLine2="           ~~~~~~~~">
        <location
            file="../gradle/libs.versions.toml"
            line="10"
            column="12"/>
    </issue>

    <issue
        id="GradleDependency"
        message="A newer version of androidx.activity:activity than 1.9.0 is available: 1.9.1"
        errorLine1="activity = &quot;1.9.0&quot;"
        errorLine2="           ~~~~~~~">
        <location
            file="../gradle/libs.versions.toml"
            line="11"
            column="12"/>
    </issue>

    <issue
        id="GradleDependency"
        message="A newer version of androidx.activity:activity than 1.9.0 is available: 1.9.1"
        errorLine1="activity = &quot;1.9.0&quot;"
        errorLine2="           ~~~~~~~">
        <location
            file="../gradle/libs.versions.toml"
            line="11"
            column="12"/>
    </issue>

    <issue
        id="GradleDependency"
        message="A newer version of androidx.activity:activity than 1.9.0 is available: 1.9.1"
        errorLine1="activity = &quot;1.9.0&quot;"
        errorLine2="           ~~~~~~~">
        <location
            file="../gradle/libs.versions.toml"
            line="11"
            column="12"/>
    </issue>

    <issue
        id="GradleDependency"
        message="A newer version of androidx.lifecycle:lifecycle-livedata-ktx than 2.8.2 is available: 2.8.4"
        errorLine1="lifecycleViewmodelKtx = &quot;2.8.2&quot;"
        errorLine2="                        ~~~~~~~">
        <location
            file="../gradle/libs.versions.toml"
            line="13"
            column="25"/>
    </issue>

    <issue
        id="GradleDependency"
        message="A newer version of androidx.lifecycle:lifecycle-livedata-ktx than 2.8.2 is available: 2.8.4"
        errorLine1="lifecycleViewmodelKtx = &quot;2.8.2&quot;"
        errorLine2="                        ~~~~~~~">
        <location
            file="../gradle/libs.versions.toml"
            line="13"
            column="25"/>
    </issue>

    <issue
        id="GradleDependency"
        message="A newer version of androidx.lifecycle:lifecycle-livedata-ktx than 2.8.2 is available: 2.8.4"
        errorLine1="lifecycleViewmodelKtx = &quot;2.8.2&quot;"
        errorLine2="                        ~~~~~~~">
        <location
            file="../gradle/libs.versions.toml"
            line="13"
            column="25"/>
    </issue>

    <issue
        id="GradleDependency"
        message="A newer version of androidx.lifecycle:lifecycle-runtime-ktx than 2.8.2 is available: 2.8.4"
        errorLine1="lifecycleViewmodelKtx = &quot;2.8.2&quot;"
        errorLine2="                        ~~~~~~~">
        <location
            file="../gradle/libs.versions.toml"
            line="13"
            column="25"/>
    </issue>

    <issue
        id="GradleDependency"
        message="A newer version of androidx.lifecycle:lifecycle-runtime-ktx than 2.8.2 is available: 2.8.4"
        errorLine1="lifecycleViewmodelKtx = &quot;2.8.2&quot;"
        errorLine2="                        ~~~~~~~">
        <location
            file="../gradle/libs.versions.toml"
            line="13"
            column="25"/>
    </issue>

    <issue
        id="GradleDependency"
        message="A newer version of androidx.lifecycle:lifecycle-runtime-ktx than 2.8.2 is available: 2.8.4"
        errorLine1="lifecycleViewmodelKtx = &quot;2.8.2&quot;"
        errorLine2="                        ~~~~~~~">
        <location
            file="../gradle/libs.versions.toml"
            line="13"
            column="25"/>
    </issue>

    <issue
        id="GradleDependency"
        message="A newer version of androidx.lifecycle:lifecycle-viewmodel than 2.8.2 is available: 2.8.4"
        errorLine1="lifecycleViewmodelKtx = &quot;2.8.2&quot;"
        errorLine2="                        ~~~~~~~">
        <location
            file="../gradle/libs.versions.toml"
            line="13"
            column="25"/>
    </issue>

    <issue
        id="GradleDependency"
        message="A newer version of androidx.lifecycle:lifecycle-viewmodel than 2.8.2 is available: 2.8.4"
        errorLine1="lifecycleViewmodelKtx = &quot;2.8.2&quot;"
        errorLine2="                        ~~~~~~~">
        <location
            file="../gradle/libs.versions.toml"
            line="13"
            column="25"/>
    </issue>

    <issue
        id="GradleDependency"
        message="A newer version of androidx.lifecycle:lifecycle-viewmodel than 2.8.2 is available: 2.8.4"
        errorLine1="lifecycleViewmodelKtx = &quot;2.8.2&quot;"
        errorLine2="                        ~~~~~~~">
        <location
            file="../gradle/libs.versions.toml"
            line="13"
            column="25"/>
    </issue>

    <issue
        id="GradleDependency"
        message="A newer version of androidx.lifecycle:lifecycle-viewmodel-ktx than 2.8.2 is available: 2.8.4"
        errorLine1="lifecycleViewmodelKtx = &quot;2.8.2&quot;"
        errorLine2="                        ~~~~~~~">
        <location
            file="../gradle/libs.versions.toml"
            line="13"
            column="25"/>
    </issue>

    <issue
        id="GradleDependency"
        message="A newer version of androidx.lifecycle:lifecycle-viewmodel-ktx than 2.8.2 is available: 2.8.4"
        errorLine1="lifecycleViewmodelKtx = &quot;2.8.2&quot;"
        errorLine2="                        ~~~~~~~">
        <location
            file="../gradle/libs.versions.toml"
            line="13"
            column="25"/>
    </issue>

    <issue
        id="GradleDependency"
        message="A newer version of androidx.lifecycle:lifecycle-viewmodel-ktx than 2.8.2 is available: 2.8.4"
        errorLine1="lifecycleViewmodelKtx = &quot;2.8.2&quot;"
        errorLine2="                        ~~~~~~~">
        <location
            file="../gradle/libs.versions.toml"
            line="13"
            column="25"/>
    </issue>

    <issue
        id="UseCompatLoadingForDrawables"
        message="Use `AppCompatResources.getDrawable()`"
        errorLine1="                            .icon(requireContext().getDrawable(ic_input_add))"
        errorLine2="                                  ~~~~~~~~~~~~~~~~~~~~~~~~~~~~~~~~~~~~~~~~~~">
        <location
            file="src/main/java/io/junrdev/github/taskee/screens/ViewTasks.kt"
            line="124"
            column="35"/>
    </issue>

    <issue
        id="LogNotTimber"
        message="Using &apos;Log&apos; instead of &apos;Timber&apos;"
        errorLine1="            Log.d(TAG, &quot;tasklist: $taskList&quot;)"
        errorLine2="            ~~~~~~~~~~~~~~~~~~~~~~~~~~~~~~~~~">
        <location
            file="src/main/java/io/junrdev/github/taskee/adapter/TaskListAdapter.kt"
            line="35"
            column="13"/>
    </issue>

    <issue
        id="StaticFieldLeak"
        message="This field leaks a context object"
        errorLine1="    val context: Context"
        errorLine2="    ~~~~~~~~~~~~~~~~~~~~">
        <location
            file="src/main/java/io/junrdev/github/taskee/viewmodel/TaskViewModel.kt"
            line="15"
            column="5"/>
    </issue>

    <issue
        id="KaptUsageInsteadOfKsp"
        message="This library supports using KSP instead of kapt, which greatly improves performance. Learn more: https://developer.android.com/studio/build/migrate-to-ksp"
        errorLine1="    kapt(libs.androidx.room.compiler)"
        errorLine2="    ~~~~~~~~~~~~~~~~~~~~~~~~~~~~~~~~~">
        <location
            file="build.gradle.kts"
            line="62"
            column="5"/>
    </issue>

    <issue
        id="InefficientWeight"
        message="Use a `layout_width` of `0dp` instead of `wrap_content` for better performance"
        errorLine1="            android:layout_width=&quot;wrap_content&quot;"
        errorLine2="            ~~~~~~~~~~~~~~~~~~~~~~~~~~~~~~~~~~~">
        <location
            file="src/main/res/layout/selectprioritydialog.xml"
            line="37"
            column="13"/>
    </issue>

    <issue
        id="InefficientWeight"
        message="Use a `layout_width` of `0dp` instead of `wrap_content` for better performance"
        errorLine1="            android:layout_width=&quot;wrap_content&quot;"
        errorLine2="            ~~~~~~~~~~~~~~~~~~~~~~~~~~~~~~~~~~~">
        <location
            file="src/main/res/layout/selectprioritydialog.xml"
            line="69"
            column="13"/>
    </issue>

    <issue
        id="InefficientWeight"
        message="Use a `layout_width` of `0dp` instead of `wrap_content` for better performance"
        errorLine1="            android:layout_width=&quot;wrap_content&quot;"
        errorLine2="            ~~~~~~~~~~~~~~~~~~~~~~~~~~~~~~~~~~~">
        <location
            file="src/main/res/layout/selectprioritydialog.xml"
            line="102"
            column="13"/>
    </issue>

    <issue
        id="UnusedResources"
        message="The resource `R.drawable.homegradientbg` appears to be unused"
        errorLine1="&lt;shape xmlns:android=&quot;http://schemas.android.com/apk/res/android&quot;"
        errorLine2="^">
        <location
            file="src/main/res/drawable/homegradientbg.xml"
            line="2"
            column="1"/>
    </issue>

    <issue
        id="UnusedResources"
        message="The resource `R.drawable.round_format_bold_24` appears to be unused"
        errorLine1="&lt;vector xmlns:android=&quot;http://schemas.android.com/apk/res/android&quot; android:height=&quot;24dp&quot; android:tint=&quot;#000000&quot; android:viewportHeight=&quot;24&quot; android:viewportWidth=&quot;24&quot; android:width=&quot;24dp&quot;>"
        errorLine2="^">
        <location
            file="src/main/res/drawable/round_format_bold_24.xml"
            line="1"
            column="1"/>
    </issue>

    <issue
        id="UnusedResources"
        message="The resource `R.style.editorstyle` appears to be unused"
        errorLine1="    &lt;style name=&quot;editorstyle&quot;>"
        errorLine2="           ~~~~~~~~~~~~~~~~~~">
        <location
            file="src/main/res/values/themes.xml"
            line="13"
            column="12"/>
    </issue>

    <issue
        id="IconLocation"
        message="Found bitmap drawable `res/drawable/bold.png` in densityless folder">
        <location
            file="src/main/res/drawable/bold.png"/>
    </issue>

    <issue
        id="IconLocation"
        message="Found bitmap drawable `res/drawable/italic.png` in densityless folder">
        <location
            file="src/main/res/drawable/italic.png"/>
    </issue>

    <issue
        id="IconLocation"
        message="Found bitmap drawable `res/drawable/list.png` in densityless folder">
        <location
            file="src/main/res/drawable/list.png"/>
    </issue>

    <issue
        id="Autofill"
        message="Missing `autofillHints` attribute"
        errorLine1="        &lt;EditText"
        errorLine2="         ~~~~~~~~">
        <location
            file="src/main/res/layout/addtaskitem.xml"
            line="26"
            column="10"/>
    </issue>

    <issue
        id="Autofill"
        message="Missing `autofillHints` attribute"
        errorLine1="        &lt;EditText"
        errorLine2="         ~~~~~~~~">
        <location
            file="src/main/res/layout/edittaskitem.xml"
            line="42"
            column="10"/>
    </issue>

    <issue
        id="ContentDescription"
        message="Missing `contentDescription` attribute on image"
        errorLine1="                &lt;ImageView"
        errorLine2="                 ~~~~~~~~~">
        <location
            file="src/main/res/layout/addtaskitem.xml"
            line="69"
            column="18"/>
    </issue>

    <issue
        id="ContentDescription"
        message="Missing `contentDescription` attribute on image"
        errorLine1="                &lt;ImageView"
        errorLine2="                 ~~~~~~~~~">
        <location
            file="src/main/res/layout/addtaskitem.xml"
            line="77"
            column="18"/>
    </issue>

    <issue
        id="ContentDescription"
        message="Missing `contentDescription` attribute on image"
        errorLine1="                &lt;ImageView"
        errorLine2="                 ~~~~~~~~~">
        <location
            file="src/main/res/layout/addtaskitem.xml"
            line="85"
            column="18"/>
    </issue>

    <issue
        id="ContentDescription"
        message="Missing `contentDescription` attribute on image"
        errorLine1="                &lt;ImageView"
        errorLine2="                 ~~~~~~~~~">
        <location
            file="src/main/res/layout/edittaskitem.xml"
            line="116"
            column="18"/>
    </issue>

    <issue
        id="ContentDescription"
        message="Missing `contentDescription` attribute on image"
        errorLine1="                &lt;ImageView"
        errorLine2="                 ~~~~~~~~~">
        <location
            file="src/main/res/layout/edittaskitem.xml"
            line="124"
            column="18"/>
    </issue>

    <issue
        id="ContentDescription"
        message="Missing `contentDescription` attribute on image"
        errorLine1="                &lt;ImageView"
        errorLine2="                 ~~~~~~~~~">
        <location
            file="src/main/res/layout/edittaskitem.xml"
            line="132"
            column="18"/>
    </issue>

    <issue
        id="ContentDescription"
        message="Missing `contentDescription` attribute on image"
        errorLine1="        &lt;ImageView"
        errorLine2="         ~~~~~~~~~">
        <location
            file="src/main/res/layout/viewsingletask.xml"
            line="66"
            column="10"/>
    </issue>

    <issue
        id="KeyboardInaccessibleWidget"
        message="&apos;clickable&apos; attribute found, please also add &apos;focusable&apos;"
        errorLine1="        android:clickable=&quot;true&quot;"
        errorLine2="        ~~~~~~~~~~~~~~~~~~~~~~~~">
        <location
            file="src/main/res/layout/selectprioritydialog.xml"
            line="22"
            column="9"/>
    </issue>

    <issue
        id="KeyboardInaccessibleWidget"
        message="&apos;clickable&apos; attribute found, please also add &apos;focusable&apos;"
        errorLine1="        android:clickable=&quot;true&quot;"
        errorLine2="        ~~~~~~~~~~~~~~~~~~~~~~~~">
        <location
            file="src/main/res/layout/selectprioritydialog.xml"
            line="54"
            column="9"/>
    </issue>

    <issue
        id="KeyboardInaccessibleWidget"
        message="&apos;clickable&apos; attribute found, please also add &apos;focusable&apos;"
        errorLine1="        android:clickable=&quot;true&quot;"
        errorLine2="        ~~~~~~~~~~~~~~~~~~~~~~~~">
        <location
            file="src/main/res/layout/selectprioritydialog.xml"
            line="87"
            column="9"/>
    </issue>

    <issue
        id="LabelFor"
        message="Missing accessibility label: provide either a view with an `android:labelFor` that references this view or provide an `android:hint`"
        errorLine1="        &lt;EditText"
        errorLine2="         ~~~~~~~~">
        <location
            file="src/main/res/layout/addtaskitem.xml"
            line="26"
            column="10"/>
    </issue>

    <issue
        id="LabelFor"
        message="Missing accessibility label: provide either a view with an `android:labelFor` that references this view or provide an `android:hint`"
        errorLine1="        &lt;EditText"
        errorLine2="         ~~~~~~~~">
        <location
            file="src/main/res/layout/edittaskitem.xml"
            line="42"
            column="10"/>
    </issue>

    <issue
        id="HardcodedText"
        message="Hardcoded string &quot;Title&quot;, should use `@string` resource"
        errorLine1="            android:text=&quot;Title&quot;"
        errorLine2="            ~~~~~~~~~~~~~~~~~~~~">
        <location
            file="src/main/res/layout/addtaskitem.xml"
            line="20"
            column="13"/>
    </issue>

    <issue
        id="HardcodedText"
        message="Hardcoded string &quot;Description&quot;, should use `@string` resource"
        errorLine1="            android:text=&quot;Description&quot;"
        errorLine2="            ~~~~~~~~~~~~~~~~~~~~~~~~~~">
        <location
            file="src/main/res/layout/addtaskitem.xml"
            line="48"
            column="13"/>
    </issue>

    <issue
        id="HardcodedText"
        message="Hardcoded string &quot;Save&quot;, should use `@string` resource"
        errorLine1="                android:text=&quot;Save&quot;"
        errorLine2="                ~~~~~~~~~~~~~~~~~~~">
        <location
            file="src/main/res/layout/addtaskitem.xml"
            line="137"
            column="17"/>
    </issue>

    <issue
        id="HardcodedText"
        message="Hardcoded string &quot;Title&quot;, should use `@string` resource"
        errorLine1="            android:text=&quot;Title&quot;"
        errorLine2="            ~~~~~~~~~~~~~~~~~~~~">
        <location
            file="src/main/res/layout/edittaskitem.xml"
            line="38"
            column="13"/>
    </issue>

    <issue
        id="HardcodedText"
        message="Hardcoded string &quot;Description&quot;, should use `@string` resource"
        errorLine1="            android:text=&quot;Description&quot;"
        errorLine2="            ~~~~~~~~~~~~~~~~~~~~~~~~~~">
        <location
            file="src/main/res/layout/edittaskitem.xml"
            line="64"
            column="13"/>
    </issue>

    <issue
        id="HardcodedText"
        message="Hardcoded string &quot;Update&quot;, should use `@string` resource"
        errorLine1="                android:text=&quot;Update&quot;"
        errorLine2="                ~~~~~~~~~~~~~~~~~~~~~">
        <location
            file="src/main/res/layout/edittaskitem.xml"
            line="96"
            column="17"/>
    </issue>

    <issue
        id="HardcodedText"
        message="Hardcoded string &quot;Normal&quot;, should use `@string` resource"
        errorLine1="            android:text=&quot;Normal&quot;"
        errorLine2="            ~~~~~~~~~~~~~~~~~~~~~">
        <location
            file="src/main/res/layout/selectprioritydialog.xml"
            line="42"
            column="13"/>
    </issue>

    <issue
        id="HardcodedText"
        message="Hardcoded string &quot;Medium&quot;, should use `@string` resource"
        errorLine1="            android:text=&quot;Medium&quot;"
        errorLine2="            ~~~~~~~~~~~~~~~~~~~~~">
        <location
            file="src/main/res/layout/selectprioritydialog.xml"
            line="74"
            column="13"/>
    </issue>

    <issue
        id="HardcodedText"
        message="Hardcoded string &quot;High&quot;, should use `@string` resource"
        errorLine1="            android:text=&quot;High&quot;"
        errorLine2="            ~~~~~~~~~~~~~~~~~~~">
        <location
            file="src/main/res/layout/selectprioritydialog.xml"
            line="107"
            column="13"/>
    </issue>

    <issue
        id="HardcodedText"
        message="Hardcoded string &quot;Done&quot;, should use `@string` resource"
        errorLine1="                android:text=&quot;Done&quot;"
        errorLine2="                ~~~~~~~~~~~~~~~~~~~">
        <location
            file="src/main/res/layout/viewsingletask.xml"
            line="34"
            column="17"/>
    </issue>

    <issue
        id="HardcodedText"
        message="Hardcoded string &quot;Add Task&quot;, should use `@string` resource"
        errorLine1="                android:text=&quot;Add Task&quot;"
        errorLine2="                ~~~~~~~~~~~~~~~~~~~~~~~">
        <location
            file="src/main/res/layout/viewtasks.xml"
            line="56"
            column="17"/>
    </issue>

    <issue
        id="RtlHardcoded"
        message="Redundant attribute `layout_marginLeft`; already defining `layout_marginStart` with `targetSdkVersion` 34"
        errorLine1="        android:layout_marginLeft=&quot;8dp&quot;"
        errorLine2="        ~~~~~~~~~~~~~~~~~~~~~~~~~">
        <location
            file="src/main/res/layout/selectprioritydialog.xml"
            line="83"
            column="9"/>
    </issue>

</issues>
